Workbook

Sheet 00_LEGENDE
A1: LÉGENDE — GRHADES E-Commerce B2C | Anomalies & Bugs
A2: ⚠ Ne pas modifier sans validation chef de projet
A4: Sévérité
B5: Bloquant
B6: Majeur
B7: Mineur
B8: Cosmétique
A10: Priorité
B11: Critique
B12: Haute
B13: Moyenne
B14: Faible
A16: Statut
B17: Ouvert
B18: En cours
B19: Résolu
B20: Fermé
B21: Rejeté
A23: Phase détection
B24: Définition
B25: Conception
B26: Réalisation
B27: Tests
B28: Recette
B29: Déploiement
A31: Phase origine
B32: Définition
B33: Conception
B34: Réalisation
B35: Tests
B36: Recette
B37: Inconnu
A39: Règles de saisie
B40: ID : ANO-NNN — unique et permanent
B41: Toute modification de statut → copier dans 03_HISTORIQUE
B42: Sévérité Bloquant = escalade immédiate au chef de projet
B43: Phase origine = phase où le défaut a été INTRODUIT (pas détecté)
B44: Date résolution = date du merge/déploiement du correctif

Sheet 01_ANOMALIES
A1: REGISTRE DES ANOMALIES — GRHADES E-Commerce B2C (15 anomalies)
A2: ID_ANO | B2: Date détection | C2: Phase détection | D2: Phase origine | E2: Titre | F2: Description / Étapes de reproduction | G2: Sévérité | H2: Priorité | I2: Statut | J2: ID_EXG lié | K2: Assigné à | L2: Date cible | M2: Date résolution | N2: Version détection | O2: Version correction | P2: Commentaires / Solution appliquée
A3: ANO-001 | B3: 10/03/2026 | C3: Tests | D3: Conception | E3: Variantes produit : images non mises à jour lors du changement de couleur | F3: Sur la fiche produit, quand l'utilisateur sélectionne une variante (ex. T-shirt Rouge → Bleu), les images de la galerie ne se mettent pas à jour. Le sélecteur OWL ne déclenche pas l'événement de rechargement d'image. | G3: Majeur | H3: Haute | I3: Résolu | J3: EXG-001 | K3: M. Amine (Dev) | L3: 15/03/2026 | M3: 14/03/2026 | N3: v0.7 | O3: v0.8 | P3: Ajout listener variant_change dans le composant OWL ProductImageCarousel. Commit #3a2f1b
A4: ANO-002 | B4: 15/03/2026 | C4: Tests | D4: Réalisation | E4: Panier : quantité non vérifiée contre stock — survente possible | F4: Lors de l'ajout au panier, la vérification de stock ne s'exécute pas si le produit est ajouté depuis la page catégorie (bouton ajout rapide). Seule la fiche produit effectue la vérification. Risque de survente. | G4: Bloquant | H4: Critique | I4: Résolu | J4: EXG-005 | K4: M. Amine (Dev) | L4: 18/03/2026 | M4: 17/03/2026 | N4: v0.7 | O4: v0.8 | P4: Vérification déplacée dans le controller /shop/cart/update (couvre tous les points d'entrée). Commit #4b3c2d
A5: ANO-003 | B5: 20/03/2026 | C5: Tests | D5: Conception | E5: Module paiement : webhook Stripe non reçu en staging | F5: Le webhook Stripe payment_intent.succeeded n'est pas reçu par le contrôleur Odoo /payment/stripe/webhook en environnement de staging. La commande reste bloquée au statut 'En attente de paiement'. Cause identifiée : signature webhook incorrecte. | G5: Bloquant | H5: Critique | I5: Résolu | J5: EXG-003 | K5: M. Yassine (Tech) | L5: 22/03/2026 | M5: 21/03/2026 | N5: v0.8 | O5: v0.8.1 | P5: Correction : endpoint_secret chargé depuis ir.config_parameter. Vérification stripe.WebhookSignature.verify_header ajoutée. Commit #5c4d3e
A6: ANO-004 | B6: 01/04/2026 | C6: Tests | D6: Réalisation | E6: Facturation automatique : TVA incorrecte pour clients hors Algérie | F6: La facture générée automatiquement applique toujours le taux de TVA algérien (19%) même pour les commandes expédiées à l'étranger. La fiscal position n'est pas détectée automatiquement depuis l'adresse de livraison. | G6: Majeur | H6: Haute | I6: Résolu | J6: EXG-007 | K6: Mme. Sara (MOA) | L6: 05/04/2026 | M6: 04/04/2026 | N6: v0.8 | O6: v0.9 | P6: Ajout auto_apply=True sur la fiscal position internationale + country_group configuré. Commit #6d5e4f
A7: ANO-005 | B7: 05/04/2026 | C7: Tests | D7: Réalisation | E7: Email confirmation commande : lien 'Voir ma commande' redirige vers erreur 403 | F7: Le lien 'Voir ma commande' dans l'email de confirmation redirige vers /my/orders/{id} mais retourne une erreur 403 si le client n'est pas connecté. Le token d'accès au portail (portal.access_token) n'est pas inclus dans l'URL. | G7: Majeur | H7: Haute | I7: Résolu | J7: EXG-008 | K7: M. Amine (Dev) | L7: 08/04/2026 | M7: 07/04/2026 | N7: v0.9 | O7: v0.9.1 | P7: Ajout du paramètre access_token dans le template QWeb de l'email. Commit #7e6f5a
A8: ANO-006 | B8: 08/04/2026 | C8: Tests | D8: Réalisation | E8: Programme fidélité : points non crédités si paiement par virement | F8: Les points de fidélité ne sont pas crédités quand la commande est payée par virement bancaire. Le trigger Python est accroché sur payment.transaction.done mais le virement valide la commande sans passer par payment.transaction. | G8: Majeur | H8: Haute | I8: Résolu | J8: EXG-011 | K8: M. Amine (Dev) | L8: 18/04/2026 | M8: 18/05/2026 | N8: v0.9 | P8: Analyse : accrocher le trigger sur account.move posted plutôt que payment.transaction
A9: ANO-007 | B9: 10/04/2026 | C9: Recette | D9: Conception | E9: Filtre prix catalogue : borne supérieure non inclusive | F9: Dans le filtre de prix du catalogue, la borne supérieure est exclusive (filtre '10€ - 50€' exclut les produits à exactement 50,00€). Erreur dans la domain Odoo : price <= 50 au lieu de price <= 50. | G9: Mineur | H9: Moyenne | I9: Résolu | J9: EXG-010 | K9: M. Amine (Dev) | L9: 11/04/2026 | M9: 10/04/2026 | N9: v0.9 | O9: v0.9.2 | P9: Correction domain : ('list_price', '<=', price_max). Commit #8f7a6b
A10: ANO-008 | B10: 12/04/2026 | C10: Recette | D10: Réalisation | E10: Module retours : avoir non généré si commande payée en CB + coupon | F10: Quand une commande a été payée en partie par coupon de réduction et en partie par CB, la génération de l'avoir échoue avec l'erreur 'Cannot reconcile credit note with multiple payment methods'. Le module grhades_returns ne gère pas ce cas. | G10: Bloquant | H10: Critique | I10: Ouvert | J10: EXG-009 | K10: M. Yassine (Tech) | L10: 19/04/2026 | N10: v0.9 | P10: Escalade CP — bloquant pour la recette retours. Analyse en cours.
A11: ANO-009 | B11: 14/04/2026 | C11: Recette | D11: Conception | E11: Dashboard KPI : CA inclut les avoirs (chiffres gonflés) | F11: Le calcul du CA dans le dashboard Odoo (SPEC-020) inclut à tort les factures d'avoir (account.move type out_refund), ce qui gonfle artificiellement le CA affiché de 6 à 12% selon les périodes. | G11: Majeur | H11: Haute | I11: Ouvert | J11: EXG-018 | K11: Mme. Sara (MOA) | L11: 19/04/2026 | N11: v0.9 | P11: Correction domain : ajouter ('move_type', '=', 'out_invoice') dans le SUMIF
A12: ANO-010 | B12: 15/04/2026 | C12: Recette | D12: Réalisation | E12: Bandeau RGPD cookies : consentement non mémorisé après fermeture navigateur | F12: Le consentement aux cookies enregistré dans le champ res.partner consent_ids est perdu quand l'utilisateur ferme et rouvre le navigateur. Le composant OWL recharge les préférences depuis le serveur mais ne les trouve pas si la session a expiré. | G12: Majeur | H12: Haute | I12: Ouvert | J12: EXG-022 | K12: M. Yassine (Tech) | L12: 21/04/2026 | N12: v0.9 | P12: Fallback nécessaire : cookie navigateur local + synchronisation serveur
A13: ANO-011 | B13: 16/04/2026 | C13: Recette | D13: Réalisation | E13: Menu mobile hamburger : fermeture impossible sur Safari iOS 17 | F13: Sur Safari iOS 17, le menu hamburger s'ouvre correctement mais ne se ferme pas au clic sur le bouton de fermeture (X). L'événement click OWL n'est pas capturé correctement sur iOS (bug connu WebKit pour les éléments position:fixed). | G13: Mineur | H13: Haute | I13: Ouvert | J13: EXG-020 | K13: M. Amine (Dev) | L13: 22/04/2026 | N13: v0.9 | P13: Solution : remplacer click par touchend pour iOS. Workaround CSS possible.
A14: ANO-012 | B14: 17/04/2026 | C14: Recette | D14: Réalisation | E14: Coupons : plafond 30% non appliqué lors du cumul fidélité + code promo | F14: Le module grhades_coupon_custom est en développement (SPEC-031) mais un test anticipé montre que l'override _check_promo_applicability ne calcule pas correctement le cumul quand les points de fidélité sont appliqués en premier. | G14: Majeur | H14: Haute | I14: Ouvert | J14: EXG-029 | K14: M. Amine (Dev) | L14: 25/04/2026 | N14: v0.9 | P14: Module en cours de dev — à corriger avant livraison sprint 4
A15: ANO-013 | B15: 18/04/2026 | C15: Recette | D15: Conception | E15: Emails en anglais envoyés en français aux clients ayant choisi EN | F15: Les emails transactionnels (confirmation commande, expédition) sont toujours envoyés en français quelle que soit la langue du partenaire (res.partner.lang). Le mail.template ne récupère pas la langue depuis res.partner mais depuis la langue de l'utilisateur connecté. | G15: Mineur | H15: Haute | I15: Ouvert | J15: EXG-008 | K15: M. Amine (Dev) | L15: 23/04/2026 | N15: v0.9 | P15: Correction : ajouter lang=partner.lang dans mail.template.send_mail(force_send=True)
A16: ANO-014 | B16: 19/04/2026 | C16: Tests | D16: Réalisation | E16: Cron paniers abandonnés : s'exécute aussi sur les commandes validées | F16: Le cron grhades_abandoned_cart sélectionne parfois des sale.order dont le state est 'sale' (commande validée) si la commande a été validée dans la fenêtre d'exécution du cron. La condition de sélection ne filtre pas correctement sur state='draft'. | G16: Majeur | H16: Haute | I16: Ouvert | J16: EXG-017 | K16: M. Amine (Dev) | L16: 21/04/2026 | N16: v0.9 | P16: Domain cron : ajouter ('state', '=', 'draft') explicitement + test unitaire
A17: ANO-015 | B17: 19/04/2026 | C17: Tests | D17: Conception | E17: Performance : page catalogue lente (> 4s) sans cache Odoo actif | F17: Sans le cache navigateur (première visite ou cache vidé), la page catalogue met 4 à 6 secondes à charger avec 80 produits affichés. Requête SQL Odoo non optimisée : N+1 queries sur product.product pour les variantes. | G17: Majeur | H17: Haute | I17: Ouvert | J17: EXG-019 | K17: M. Yassine (Tech) | L17: 24/04/2026 | N17: v0.9 | P17: Optimisation : prefetch_record_ids sur product.product + pagination stricte 24 produits

Sheet 02_SYNTHESE_PHASE
A1: TABLEAU DE BORD — Anomalies par Phase & Sévérité
A2: ⟳ Formules automatiques
A3: Phase (détection) | B3: Total | C3: Ouvertes | D3: En cours | E3: Résolues | F3: Fermées | G3: Rejetées | H3: Bloquantes | I3: Majeures | J3: Mineures | K3: % Résolues
A4: Définition | B4: =COUNTIF('01_ANOMALIES'!$C$3:$C$200,"Définition") -> 0 | C4: =COUNTIFS('01_ANOMALIES'!$C$3:$C$200,"Définition",'01_ANOMALIES'!$I$3:$I$200,"Ouvert") -> 0 | D4: =COUNTIFS('01_ANOMALIES'!$C$3:$C$200,"Définition",'01_ANOMALIES'!$I$3:$I$200,"En cours") -> 0 | E4: =COUNTIFS('01_ANOMALIES'!$C$3:$C$200,"Définition",'01_ANOMALIES'!$I$3:$I$200,"Résolu") -> 0 | F4: =COUNTIFS('01_ANOMALIES'!$C$3:$C$200,"Définition",'01_ANOMALIES'!$I$3:$I$200,"Fermé") -> 0 | G4: =COUNTIFS('01_ANOMALIES'!$C$3:$C$200,"Définition",'01_ANOMALIES'!$I$3:$I$200,"Rejeté") -> 0 | H4: =COUNTIFS('01_ANOMALIES'!$C$3:$C$200,"Définition",'01_ANOMALIES'!$G$3:$G$200,"Bloquant") -> 0 | I4: =COUNTIFS('01_ANOMALIES'!$C$3:$C$200,"Définition",'01_ANOMALIES'!$G$3:$G$200,"Majeur") -> 0 | J4: =COUNTIFS('01_ANOMALIES'!$C$3:$C$200,"Définition",'01_ANOMALIES'!$G$3:$G$200,"Mineur") -> 0 | K4: =IF(B4=0,0,(E4+F4)/B4) -> 0
A5: Conception | B5: =COUNTIF('01_ANOMALIES'!$C$3:$C$200,"Conception") -> 0 | C5: =COUNTIFS('01_ANOMALIES'!$C$3:$C$200,"Conception",'01_ANOMALIES'!$I$3:$I$200,"Ouvert") -> 0 | D5: =COUNTIFS('01_ANOMALIES'!$C$3:$C$200,"Conception",'01_ANOMALIES'!$I$3:$I$200,"En cours") -> 0 | E5: =COUNTIFS('01_ANOMALIES'!$C$3:$C$200,"Conception",'01_ANOMALIES'!$I$3:$I$200,"Résolu") -> 0 | F5: =COUNTIFS('01_ANOMALIES'!$C$3:$C$200,"Conception",'01_ANOMALIES'!$I$3:$I$200,"Fermé") -> 0 | G5: =COUNTIFS('01_ANOMALIES'!$C$3:$C$200,"Conception",'01_ANOMALIES'!$I$3:$I$200,"Rejeté") -> 0 | H5: =COUNTIFS('01_ANOMALIES'!$C$3:$C$200,"Conception",'01_ANOMALIES'!$G$3:$G$200,"Bloquant") -> 0 | I5: =COUNTIFS('01_ANOMALIES'!$C$3:$C$200,"Conception",'01_ANOMALIES'!$G$3:$G$200,"Majeur") -> 0 | J5: =COUNTIFS('01_ANOMALIES'!$C$3:$C$200,"Conception",'01_ANOMALIES'!$G$3:$G$200,"Mineur") -> 0 | K5: =IF(B5=0,0,(E5+F5)/B5) -> 0
A6: Réalisation | B6: =COUNTIF('01_ANOMALIES'!$C$3:$C$200,"Réalisation") -> 0 | C6: =COUNTIFS('01_ANOMALIES'!$C$3:$C$200,"Réalisation",'01_ANOMALIES'!$I$3:$I$200,"Ouvert") -> 0 | D6: =COUNTIFS('01_ANOMALIES'!$C$3:$C$200,"Réalisation",'01_ANOMALIES'!$I$3:$I$200,"En cours") -> 0 | E6: =COUNTIFS('01_ANOMALIES'!$C$3:$C$200,"Réalisation",'01_ANOMALIES'!$I$3:$I$200,"Résolu") -> 0 | F6: =COUNTIFS('01_ANOMALIES'!$C$3:$C$200,"Réalisation",'01_ANOMALIES'!$I$3:$I$200,"Fermé") -> 0 | G6: =COUNTIFS('01_ANOMALIES'!$C$3:$C$200,"Réalisation",'01_ANOMALIES'!$I$3:$I$200,"Rejeté") -> 0 | H6: =COUNTIFS('01_ANOMALIES'!$C$3:$C$200,"Réalisation",'01_ANOMALIES'!$G$3:$G$200,"Bloquant") -> 0 | I6: =COUNTIFS('01_ANOMALIES'!$C$3:$C$200,"Réalisation",'01_ANOMALIES'!$G$3:$G$200,"Majeur") -> 0 | J6: =COUNTIFS('01_ANOMALIES'!$C$3:$C$200,"Réalisation",'01_ANOMALIES'!$G$3:$G$200,"Mineur") -> 0 | K6: =IF(B6=0,0,(E6+F6)/B6) -> 0
A7: Tests | B7: =COUNTIF('01_ANOMALIES'!$C$3:$C$200,"Tests") -> 8 | C7: =COUNTIFS('01_ANOMALIES'!$C$3:$C$200,"Tests",'01_ANOMALIES'!$I$3:$I$200,"Ouvert") -> 2 | D7: =COUNTIFS('01_ANOMALIES'!$C$3:$C$200,"Tests",'01_ANOMALIES'!$I$3:$I$200,"En cours") -> 0 | E7: =COUNTIFS('01_ANOMALIES'!$C$3:$C$200,"Tests",'01_ANOMALIES'!$I$3:$I$200,"Résolu") -> 6 | F7: =COUNTIFS('01_ANOMALIES'!$C$3:$C$200,"Tests",'01_ANOMALIES'!$I$3:$I$200,"Fermé") -> 0 | G7: =COUNTIFS('01_ANOMALIES'!$C$3:$C$200,"Tests",'01_ANOMALIES'!$I$3:$I$200,"Rejeté") -> 0 | H7: =COUNTIFS('01_ANOMALIES'!$C$3:$C$200,"Tests",'01_ANOMALIES'!$G$3:$G$200,"Bloquant") -> 2 | I7: =COUNTIFS('01_ANOMALIES'!$C$3:$C$200,"Tests",'01_ANOMALIES'!$G$3:$G$200,"Majeur") -> 6 | J7: =COUNTIFS('01_ANOMALIES'!$C$3:$C$200,"Tests",'01_ANOMALIES'!$G$3:$G$200,"Mineur") -> 0 | K7: =IF(B7=0,0,(E7+F7)/B7) -> 0.75
A8: Recette | B8: =COUNTIF('01_ANOMALIES'!$C$3:$C$200,"Recette") -> 7 | C8: =COUNTIFS('01_ANOMALIES'!$C$3:$C$200,"Recette",'01_ANOMALIES'!$I$3:$I$200,"Ouvert") -> 6 | D8: =COUNTIFS('01_ANOMALIES'!$C$3:$C$200,"Recette",'01_ANOMALIES'!$I$3:$I$200,"En cours") -> 0 | E8: =COUNTIFS('01_ANOMALIES'!$C$3:$C$200,"Recette",'01_ANOMALIES'!$I$3:$I$200,"Résolu") -> 1 | F8: =COUNTIFS('01_ANOMALIES'!$C$3:$C$200,"Recette",'01_ANOMALIES'!$I$3:$I$200,"Fermé") -> 0 | G8: =COUNTIFS('01_ANOMALIES'!$C$3:$C$200,"Recette",'01_ANOMALIES'!$I$3:$I$200,"Rejeté") -> 0 | H8: =COUNTIFS('01_ANOMALIES'!$C$3:$C$200,"Recette",'01_ANOMALIES'!$G$3:$G$200,"Bloquant") -> 1 | I8: =COUNTIFS('01_ANOMALIES'!$C$3:$C$200,"Recette",'01_ANOMALIES'!$G$3:$G$200,"Majeur") -> 3 | J8: =COUNTIFS('01_ANOMALIES'!$C$3:$C$200,"Recette",'01_ANOMALIES'!$G$3:$G$200,"Mineur") -> 3 | K8: =IF(B8=0,0,(E8+F8)/B8) -> 0.14285714
A9: Déploiement | B9: =COUNTIF('01_ANOMALIES'!$C$3:$C$200,"Déploiement") -> 0 | C9: =COUNTIFS('01_ANOMALIES'!$C$3:$C$200,"Déploiement",'01_ANOMALIES'!$I$3:$I$200,"Ouvert") -> 0 | D9: =COUNTIFS('01_ANOMALIES'!$C$3:$C$200,"Déploiement",'01_ANOMALIES'!$I$3:$I$200,"En cours") -> 0 | E9: =COUNTIFS('01_ANOMALIES'!$C$3:$C$200,"Déploiement",'01_ANOMALIES'!$I$3:$I$200,"Résolu") -> 0 | F9: =COUNTIFS('01_ANOMALIES'!$C$3:$C$200,"Déploiement",'01_ANOMALIES'!$I$3:$I$200,"Fermé") -> 0 | G9: =COUNTIFS('01_ANOMALIES'!$C$3:$C$200,"Déploiement",'01_ANOMALIES'!$I$3:$I$200,"Rejeté") -> 0 | H9: =COUNTIFS('01_ANOMALIES'!$C$3:$C$200,"Déploiement",'01_ANOMALIES'!$G$3:$G$200,"Bloquant") -> 0 | I9: =COUNTIFS('01_ANOMALIES'!$C$3:$C$200,"Déploiement",'01_ANOMALIES'!$G$3:$G$200,"Majeur") -> 0 | J9: =COUNTIFS('01_ANOMALIES'!$C$3:$C$200,"Déploiement",'01_ANOMALIES'!$G$3:$G$200,"Mineur") -> 0 | K9: =IF(B9=0,0,(E9+F9)/B9) -> 0
A10: TOTAL | B10: =SUM(B4:B9) -> 15 | C10: =SUM(C4:C9) -> 8 | D10: =SUM(D4:D9) -> 0 | E10: =SUM(E4:E9) -> 7 | F10: =SUM(F4:F9) -> 0 | G10: =SUM(G4:G9) -> 0 | H10: =SUM(H4:H9) -> 3 | I10: =SUM(I4:I9) -> 9 | J10: =SUM(J4:J9) -> 3 | K10: =IF(B10=0,0,(E10+F10)/B10) -> 0.46666667

Sheet 03_HISTORIQUE
A1: HISTORIQUE DES CHANGEMENTS — Journal Immuable GRHADES (27 entrées)
A2: 🔒 Ne jamais supprimer de ligne — ajouter une nouvelle ligne à chaque changement de statut
A3: Horodatage | B3: ID_ANO | C3: Ancien statut | D3: Nouveau statut | E3: Modifié par | F3: Version | G3: Commentaire
A4: 10/03/2026 09:00 | B4: ANO-001 | C4: — | D4: Ouvert | E4: M. Amine | F4: v0.7 | G4: Anomalie détectée lors des tests composant OWL variantes
A5: 12/03/2026 14:30 | B5: ANO-001 | C5: Ouvert | D5: En cours | E5: M. Amine | F5: v0.7 | G5: Analyse du composant OWL ProductImageCarousel en cours
A6: 14/03/2026 11:00 | B6: ANO-001 | C6: En cours | D6: Résolu | E6: M. Amine | F6: v0.8 | G6: Listener variant_change ajouté — tests OK sur 5 produits avec variantes
A7: 15/03/2026 10:00 | B7: ANO-002 | C7: — | D7: Ouvert | E7: M. Amine | F7: v0.7 | G7: Survente possible détectée — signalée immédiatement au CP
A8: 15/03/2026 10:05 | B8: ANO-002 | C8: Ouvert | D8: En cours | E8: M. Yassine | F8: v0.7 | G8: Escalade CP — correction priorité Critique
A9: 17/03/2026 09:00 | B9: ANO-002 | C9: En cours | D9: Résolu | E9: M. Amine | F9: v0.8 | G9: Vérification stock dans controller /shop/cart/update — tests OK
A10: 20/03/2026 11:30 | B10: ANO-003 | C10: — | D10: Ouvert | E10: M. Yassine | F10: v0.8 | G10: Webhook Stripe bloqué — toutes commandes staging en attente
A11: 20/03/2026 11:35 | B11: ANO-003 | C11: Ouvert | D11: En cours | E11: M. Yassine | F11: v0.8 | G11: Escalade CP — impact critique sur avancement des tests
A12: 21/03/2026 17:00 | B12: ANO-003 | C12: En cours | D12: Résolu | E12: M. Yassine | F12: v0.8.1 | G12: endpoint_secret corrigé dans ir.config_parameter — webhook OK
A13: 01/04/2026 14:00 | B13: ANO-004 | C13: — | D13: Ouvert | E13: Mme. Sara | F13: v0.8 | G13: TVA incorrecte détectée lors des tests commandes internationales
A14: 03/04/2026 10:00 | B14: ANO-004 | C14: Ouvert | D14: En cours | E14: Mme. Sara | F14: v0.8 | G14: Analyse fiscal position — auto_apply manquant identifié
... A30: 19/04/2026 10:00 | B30: ANO-015 | C30: — | D30: Ouvert | E30: M. Yassine | F30: v0.9 | G30: Performance page catalogue — 4-6s sans cache
